MANIFEST.in
README.txt
setup.py
lib/Modhex.egg-info/PKG-INFO
lib/Modhex.egg-info/SOURCES.txt
lib/Modhex.egg-info/dependency_links.txt
lib/Modhex.egg-info/top_level.txt
lib/Modhex.egg-info/zip-safe
lib/modhex/__init__.py