Metadata-Version: 1.0
Name: Modhex
Version: 0.1
Summary: Translate yubikey one-time passwords to modhex regardless of keyboard layout.
Home-page: UNKNOWN
Author: Daniel Holth
Author-email: dholth@fastmail.fm
License: UNKNOWN
Platform: UNKNOWN
